dsf/__init__.py
dsf/exceptions.py
dsf/http.py
dsf/utils.py
dsf/commands/__init__.py
dsf/commands/base_command.py
dsf/commands/code.py
dsf/commands/code_channel.py
dsf/commands/code_flags.py
dsf/commands/code_interception.py
dsf/commands/code_parameter.py
dsf/commands/code_type.py
dsf/commands/condition_type.py
dsf/commands/files.py
dsf/commands/generic.py
dsf/commands/http_endpoints.py
dsf/commands/model_subscription.py
dsf/commands/object_model.py
dsf/commands/packages.py
dsf/commands/plugins.py
dsf/commands/responses.py
dsf/commands/user_sessions.py
dsf/connections/__init__.py
dsf/connections/base_command_connection.py
dsf/connections/base_connection.py
dsf/connections/command_connection.py
dsf/connections/exceptions.py
dsf/connections/intercept_connection.py
dsf/connections/subscribe_connection.py
dsf/connections/init_messages/__init__.py
dsf/connections/init_messages/client_init_messages.py
dsf/connections/init_messages/server_init_message.py
dsf/object_model/__init__.py
dsf/object_model/model_collection.py
dsf/object_model/model_dictionary.py
dsf/object_model/model_object.py
dsf/object_model/object_model.py
dsf/object_model/utils.py
dsf/object_model/boards/__init__.py
dsf/object_model/boards/accelerometer.py
dsf/object_model/boards/board_closed_loop.py
dsf/object_model/boards/boards.py
dsf/object_model/boards/driver.py
dsf/object_model/boards/driver_closed_loop.py
dsf/object_model/boards/inductive_sensor.py
dsf/object_model/boards/min_max_current.py
dsf/object_model/boards/direct_display/__init__.py
dsf/object_model/boards/direct_display/direct_display.py
dsf/object_model/boards/direct_display/direct_display_controller.py
dsf/object_model/boards/direct_display/direct_display_encoder.py
dsf/object_model/boards/direct_display/direct_display_screen.py
dsf/object_model/boards/direct_display/direct_display_screen_st7567.py
dsf/object_model/directories/__init__.py
dsf/object_model/directories/directories.py
dsf/object_model/fans/__init__.py
dsf_python-3.6.0.dist-info/licenses/LICENSE
dsf_python-3.6.0.dist-info/METADATA
dsf_python-3.6.0.dist-info/WHEEL
dsf_python-3.6.0.dist-info/top_level.txt
dsf_python-3.6.0.dist-info/RECORD
