Metadata-Version: 2.4
Name: dsf-python
Version: 3.6.0
Summary: Python interface to access DuetSoftwareFramework
Home-page: https://github.com/Duet3D/dsf-python
Author: Duet3D Ltd.
Author-email: pkg@duet3d.com
Project-URL: Duet3D Support, https://forum.duet3d.com/
Project-URL: Bug Reports, https://github.com/Duet3D/dsf-python/issues
Project-URL: Source, https://github.com/Duet3D/dsf-python/
Keywords: Duet3D,DuetSoftwareFramework,DSF,dsf-python
Classifier: Development Status :: 5 - Production/Stable
Classifier: Intended Audience :: Developers
Classifier: Topic :: Software Development :: Libraries
Classifier: License :: OSI Approved :: GNU Lesser General Public License v3 (LGPLv3)
Classifier: Programming Language :: Python :: 3
Classifier: Programming Language :: Python :: 3.7
Classifier: Programming Language :: Python :: 3.8
Classifier: Programming Language :: Python :: 3.9
Classifier: Programming Language :: Python :: 3.10
Classifier: Programming Language :: Python :: 3.11
Classifier: Programming Language :: Python :: 3.12
Classifier: Programming Language :: Python :: 3.13
Classifier: Programming Language :: Python :: 3 :: Only
Requires-Python: >=3.7, <4
License-File: LICENSE
Requires-Dist: python-dateutil
Provides-Extra: dev
Requires-Dist: sphinx; extra == "dev"
Requires-Dist: tox; extra == "dev"
Dynamic: author
Dynamic: author-email
Dynamic: classifier
Dynamic: description
Dynamic: description-content-type
Dynamic: home-page
Dynamic: keywords
Dynamic: license-file
Dynamic: project-url
Dynamic: provides-extra
Dynamic: requires-dist
Dynamic: requires-python
Dynamic: summary
